[
  {
    "date": "2023-01-10",
    "ticker": "PETR4",
    "operation": "buy",
    "quantity": 100,
    "price": 28.50,
    "fees": 5.20
  },
  {
    "date": "2023-01-15",
    "ticker": "VALE3",
    "operation": "buy",
    "quantity": 50,
    "price": 75.30,
    "fees": 7.50
  },
  {
    "date": "2023-02-05",
    "ticker": "PETR4",
    "operation": "sell",
    "quantity": 50,
    "price": 32.75,
    "fees": 6.10
  },
  {
    "date": "2023-03-20",
    "ticker": "ITUB4",
    "operation": "buy",
    "quantity": 200,
    "price": 24.15,
    "fees": 9.60
  }
]